opticalglass/__init__.py
opticalglass/buchdahl.py
opticalglass/caselessDictionary.py
opticalglass/cdgm.py
opticalglass/glass.py
opticalglass/glasserror.py
opticalglass/glassfactory.py
opticalglass/glassmap.py
opticalglass/glassmapviewer.py
opticalglass/glasspolygons.py
opticalglass/hikari.py
opticalglass/hoya.py
opticalglass/modelglass.py
opticalglass/ohara.py
opticalglass/openpyxl_script.py
opticalglass/optical_glass_agf_class.py
opticalglass/opticalmedium.py
opticalglass/rindexinfo.py
opticalglass/schott.py
opticalglass/spectral_lines.py
opticalglass/sumita.py
opticalglass/util.py
opticalglass/data/CDGM.xls
opticalglass/data/HIKARI.xlsx
opticalglass/data/HIKARI_prev.xls
opticalglass/data/HOYA.xlsx
opticalglass/data/HOYA_prev.xlsx
opticalglass/data/OHARA.xlsx
opticalglass/data/OHARA_prev.xlsx
opticalglass/data/SCHOTT.xls
opticalglass/data/SCHOTT_prev.xls
opticalglass/data/SUMITA.xlsx
opticalglass/data/robb1983_data_final.txt
opticalglass/data/~$HIKARI.xlsx
opticalglass/test/cmd_line_example.py
opticalglass/test/test_cdgm.py
opticalglass/test/test_create_glass.py
opticalglass/test/test_glassfactory.py
opticalglass/test/test_hikari.py
opticalglass/test/test_hoya.py
opticalglass/test/test_ohara.py
opticalglass/test/test_schott.py
opticalglass/test/test_sumita.py
opticalglass/test/test_transmission.py
opticalglass/test/util.py
opticalglass-1.1.1.dist-info/licenses/LICENSE
opticalglass-1.1.1.dist-info/METADATA
opticalglass-1.1.1.dist-info/WHEEL
opticalglass-1.1.1.dist-info/entry_points.txt
opticalglass-1.1.1.dist-info/top_level.txt
opticalglass-1.1.1.dist-info/RECORD
