Metadata-Version: 2.4
Name: opticalglass
Version: 1.1.1
Summary: Tools for reading optical glass catalogs
Home-page: https://github.com/mjhoptics/opticalglass
Author: Michael J Hayford
Author-email: mjhoptics@gmail.com
License: BSD-3-Clause
Keywords: glass, optical glass, refractive index, optics,,glass catalog
Platform: any
Classifier: Programming Language :: Python :: 3.11
Classifier: Programming Language :: Python :: 3.12
Classifier: Programming Language :: Python :: 3.13
Classifier: License :: OSI Approved :: BSD License
Classifier: Operating System :: OS Independent
Classifier: Topic :: Scientific/Engineering :: Physics
Requires-Python: >=3.11
License-File: LICENSE
Requires-Dist: numpy>=2.3.1
Requires-Dist: scipy>=1.16.0
Requires-Dist: matplotlib>=3.10.3
Requires-Dist: pandas>=2.3.0
Requires-Dist: xlrd>=2.0.1
Requires-Dist: openpyxl>=3.1.5
Requires-Dist: requests>=2.32.4
Requires-Dist: json_tricks>=3.17.3
Requires-Dist: pyyaml>=6.0.2
Requires-Dist: pyside6>=6.9.1
Provides-Extra: testing
Requires-Dist: setuptools; extra == "testing"
Requires-Dist: pytest; extra == "testing"
Requires-Dist: pytest-cov; extra == "testing"
Dynamic: license-file
